abilian/.DS_Store
abilian/__init__.py
abilian/app.py
abilian/cli/__init__.py
abilian/cli/base.py
abilian/cli/config.py
abilian/cli/indexing.py
abilian/config.py
abilian/core/__init__.py
abilian/core/celery.py
abilian/core/default_logging.yml
abilian/core/entities.py
abilian/core/extensions/__init__.py
abilian/core/extensions/csrf.py
abilian/core/extensions/jinjaext.py
abilian/core/extensions/login.py
abilian/core/extensions/redis.py
abilian/core/extensions/upstream_info.py
abilian/core/logging.py
abilian/core/models/__init__.py
abilian/core/models/attachment.py
abilian/core/models/base.py
abilian/core/models/blob.py
abilian/core/models/comment.py
abilian/core/models/owned.py
abilian/core/models/subjects.py
abilian/core/models/tag.py
abilian/core/models/tests/__init__.py
abilian/core/models/tests/test_blob.py
abilian/core/models/tests/test_comment.py
abilian/core/models/tests/test_subject.py
abilian/core/signals.py
abilian/core/singleton.py
abilian/core/sqlalchemy.py
abilian/core/tests/__init__.py
abilian/core/tests/dummy.py
abilian/core/tests/test_entities.py
abilian/core/tests/test_permissions.py
abilian/core/tests/test_sa_extensions.py
abilian/core/tests/test_singleton.py
abilian/core/tests/test_utils.py
abilian/core/util.py
abilian/i18n.py
abilian/services/__init__.py
abilian/services/activity/__init__.py
abilian/services/activity/models.py
abilian/services/activity/service.py
abilian/services/activity/tests.py
abilian/services/antivirus/__init__.py
abilian/services/antivirus/service.py
abilian/services/audit/__init__.py
abilian/services/audit/models.py
abilian/services/audit/service.py
abilian/services/audit/tests.py
abilian/services/auth/__init__.py
abilian/services/auth/models.py
abilian/services/auth/service.py
abilian/services/auth/templates/login/email/password_reset_instructions.fr.txt
abilian/services/auth/templates/login/email/password_reset_instructions.txt
abilian/services/auth/templates/login/forgotten_password.html
src/abilian_core.egg-info/PKG-INFO
src/abilian_core.egg-info/SOURCES.txt
src/abilian_core.egg-info/dependency_links.txt
src/abilian_core.egg-info/requires.txt
src/abilian_core.egg-info/top_level.txt
abilian_core-0.11.24.dist-info/LICENSE.txt
abilian_core-0.11.24.dist-info/WHEEL
abilian_core-0.11.24.dist-info/METADATA
abilian_core-0.11.24.dist-info/RECORD
