Metadata-Version: 2.1
Name: abilian-core
Version: 0.11.23
Summary: A framework for enterprise applications (CRM, ERP, collaboration...).
Home-page: UNKNOWN
Author: Abilian SAS
License: LGPL-2.0-or-later
Project-URL: repository, https://github.com/abilian/abilian-core
Platform: UNKNOWN
Requires-Python: ==3.*,>=3.8.0
Provides-Extra: dev
License-File: LICENSE.txt
